shirokane_tools/__init__.py
shirokane_tools/qsub_tasks.py
shirokane_tools-0.1.0.dist-info/entry_points.txt
shirokane_tools-0.1.0.dist-info/WHEEL
shirokane_tools-0.1.0.dist-info/METADATA
shirokane_tools-0.1.0.dist-info/RECORD
