Metadata-Version: 2.1
Name: shirokane-tools
Version: 0.1.0
Summary: My SHIROKANE tools
License: MIT
Author: Hiroki Konishi
Author-email: relastle@gmail.com
Requires-Python: >=3.6,<4.0
Classifier: License :: OSI Approved :: MIT License
Classifier: Programming Language :: Python :: 3
Classifier: Programming Language :: Python :: 3.6
Classifier: Programming Language :: Python :: 3.7
Classifier: Programming Language :: Python :: 3.8
